pybotx_smartapp_smart_logger/__init__.py
pybotx_smartapp_smart_logger/py.typed
pybotx_smartapp_smart_logger/smartapp_exception_handler.py
pybotx_smartapp_smart_logger-0.2.6.dist-info/LICENSE
pybotx_smartapp_smart_logger-0.2.6.dist-info/WHEEL
pybotx_smartapp_smart_logger-0.2.6.dist-info/METADATA
pybotx_smartapp_smart_logger-0.2.6.dist-info/RECORD
