Metadata-Version: 2.1
Name: pybotx-smartapp-smart-logger
Version: 0.2.6
Summary: 
Author: Arseniy Zhiltsov
Author-email: arseniy.zhiltsov@ccsteam.ru
Requires-Python: >=3.8,<3.11
Classifier: Programming Language :: Python :: 3
Classifier: Programming Language :: Python :: 3.10
Classifier: Programming Language :: Python :: 3.8
Classifier: Programming Language :: Python :: 3.9
Requires-Dist: pybotx (>=0.42.0,<0.45.0)
Requires-Dist: pybotx-smart-logger (>=0.6.7,<0.8.0)
Requires-Dist: pybotx-smartapp-rpc (>=0.5.0,<0.6.0)
